fastmm.libs/libgomp-e985bcbb.so.1.0.0
fastmm.libs/libboost_serialization-3aa46b41.so.1.66.0
fastmm-0.2.0.dist-info/WHEEL
fastmm-0.2.0.dist-info/METADATA
fastmm-0.2.0.dist-info/RECORD
fastmm-0.2.0.dist-info/licenses/LICENSE.TXT
fastmm/__init__.pyi
fastmm/_version.py
fastmm/libfastmmlib.so
fastmm/_version.pyi
fastmm/fastmm.cpython-312-x86_64-linux-gnu.so
fastmm/fastmm.pyi
fastmm/__init__.py
