Metadata-Version: 2.4
Name: fastmm
Version: 0.2.0
Summary: Fast Map Matching - High-performance map matching library
Keywords: map-matching,gps,trajectory,routing,GIS
Author: kodonnell
License-Expression: MIT
Classifier: Development Status :: 4 - Beta
Classifier: Intended Audience :: Developers
Classifier: Intended Audience :: Science/Research
Classifier: Programming Language :: Python :: 3
Classifier: Programming Language :: Python :: 3.8
Classifier: Programming Language :: Python :: 3.9
Classifier: Programming Language :: Python :: 3.10
Classifier: Programming Language :: Python :: 3.11
Classifier: Programming Language :: Python :: 3.12
Classifier: Programming Language :: Python :: 3.13
Classifier: Programming Language :: Python :: 3.14
Classifier: Programming Language :: C++
Classifier: Topic :: Scientific/Engineering :: GIS
Project-URL: Homepage, https://github.com/kodonnell/fastmm
Project-URL: Documentation, https://github.com/kodonnell/fastmm
Project-URL: Repository, https://github.com/kodonnell/fastmm
Requires-Python: >=3.8
Provides-Extra: matcher
Provides-Extra: dev
Requires-Dist: pytest; extra == "dev"
Requires-Dist: ruff; extra == "dev"
